setup.py
ls_distributions/Binomialdistribution.py
ls_distributions/Gaussiandistribution.py
ls_distributions/Generaldistribution.py
ls_distributions/__init__.py
ls_distributions.egg-info/PKG-INFO
ls_distributions.egg-info/SOURCES.txt
ls_distributions.egg-info/dependency_links.txt
ls_distributions.egg-info/not-zip-safe
ls_distributions.egg-info/top_level.txt