Metadata-Version: 1.0
Name: ls-distributions
Version: 1.0
Summary: Gaussian and Binomial distributions
Home-page: UNKNOWN
Author: Li Shuang
Author-email: li.shuang.0425@hotmail.com
License: UNKNOWN
Platform: UNKNOWN
